LICENSE
MANIFEST.in
README.md
requirements.txt
setup.cfg
setup.py
django_mp_stock.egg-info/PKG-INFO
django_mp_stock.egg-info/SOURCES.txt
django_mp_stock.egg-info/dependency_links.txt
django_mp_stock.egg-info/requires.txt
django_mp_stock.egg-info/top_level.txt
stock/__init__.py
stock/constants.py
stock/forms.py
stock/models.py
stock/urls.py
stock/views.py
stock/locale/ru/LC_MESSAGES/django.mo
stock/locale/ru/LC_MESSAGES/django.po
stock/locale/uk/LC_MESSAGES/django.mo
stock/locale/uk/LC_MESSAGES/django.po
stock/templates/stock/report.html
stock/templatetags/__init__.py
stock/templatetags/stock.py