Metadata-Version: 2.1
Name: django-mp-stock
Version: 1.0.3
Summary: Django stock apps
Home-page: https://github.com/pmaigutyak/mp-stock
Author: Paul Maigutyak
Author-email: pmaigutyak@gmail.com
License: MIT
Download-URL: https://github.com/pmaigutyak/mp-stock/archive/1.0.3.tar.gz
Platform: UNKNOWN
License-File: LICENSE
